<annotation>
	<folder>yolo_comibined</folder>
	<filename>K000363593.JPG</filename>
	<path>C:\Users\sichu\Desktop\yolo_comibined\K000363593.JPG</path>
	<source>
		<database>Unknown</database>
	</source>
	<size>
		<width>1169</width>
		<height>1764</height>
		<depth>3</depth>
	</size>
	<segmented>0</segmented>
	<object>
		<name>Color Chart</name>
		<pose>Unspecified</pose>
		<truncated>1</truncated>
		<difficult>0</difficult>
		<bndbox>
			<xmin>1</xmin>
			<ymin>81</ymin>
			<xmax>107</xmax>
			<ymax>263</ymax>
		</bndbox>
	</object>
	<object>
		<name>Color Chart</name>
		<pose>Unspecified</pose>
		<truncated>1</truncated>
		<difficult>0</difficult>
		<bndbox>
			<xmin>1</xmin>
			<ymin>356</ymin>
			<xmax>118</xmax>
			<ymax>896</ymax>
		</bndbox>
	</object>
	<object>
		<name>Color Chart</name>
		<pose>Unspecified</pose>
		<truncated>0</truncated>
		<difficult>0</difficult>
		<bndbox>
			<xmin>46</xmin>
			<ymin>912</ymin>
			<xmax>120</xmax>
			<ymax>1634</ymax>
		</bndbox>
	</object>
	<object>
		<name>Scale</name>
		<pose>Unspecified</pose>
		<truncated>1</truncated>
		<difficult>0</difficult>
		<bndbox>
			<xmin>1</xmin>
			<ymin>909</ymin>
			<xmax>48</xmax>
			<ymax>1652</ymax>
		</bndbox>
	</object>
	<object>
		<name>Label</name>
		<pose>Unspecified</pose>
		<truncated>0</truncated>
		<difficult>0</difficult>
		<bndbox>
			<xmin>132</xmin>
			<ymin>1212</ymin>
			<xmax>491</xmax>
			<ymax>1347</ymax>
		</bndbox>
	</object>
	<object>
		<name>Label</name>
		<pose>Unspecified</pose>
		<truncated>0</truncated>
		<difficult>0</difficult>
		<bndbox>
			<xmin>762</xmin>
			<ymin>1300</ymin>
			<xmax>1145</xmax>
			<ymax>1424</ymax>
		</bndbox>
	</object>
	<object>
		<name>Label</name>
		<pose>Unspecified</pose>
		<truncated>0</truncated>
		<difficult>0</difficult>
		<bndbox>
			<xmin>785</xmin>
			<ymin>1444</ymin>
			<xmax>1132</xmax>
			<ymax>1512</ymax>
		</bndbox>
	</object>
	<object>
		<name>Label</name>
		<pose>Unspecified</pose>
		<truncated>0</truncated>
		<difficult>0</difficult>
		<bndbox>
			<xmin>480</xmin>
			<ymin>1555</ymin>
			<xmax>792</xmax>
			<ymax>1636</ymax>
		</bndbox>
	</object>
	<object>
		<name>Label</name>
		<pose>Unspecified</pose>
		<truncated>0</truncated>
		<difficult>0</difficult>
		<bndbox>
			<xmin>328</xmin>
			<ymin>1353</ymin>
			<xmax>645</xmax>
			<ymax>1420</ymax>
		</bndbox>
	</object>
	<object>
		<name>Scale</name>
		<pose>Unspecified</pose>
		<truncated>0</truncated>
		<difficult>0</difficult>
		<bndbox>
			<xmin>615</xmin>
			<ymin>461</ymin>
			<xmax>761</xmax>
			<ymax>1088</ymax>
		</bndbox>
	</object>
	<object>
		<name>Barcode</name>
		<pose>Unspecified</pose>
		<truncated>0</truncated>
		<difficult>0</difficult>
		<bndbox>
			<xmin>117</xmin>
			<ymin>28</ymin>
			<xmax>306</xmax>
			<ymax>106</ymax>
		</bndbox>
	</object>
	<object>
		<name>Barcode</name>
		<pose>Unspecified</pose>
		<truncated>0</truncated>
		<difficult>0</difficult>
		<bndbox>
			<xmin>110</xmin>
			<ymin>150</ymin>
			<xmax>301</xmax>
			<ymax>237</ymax>
		</bndbox>
	</object>
	<object>
		<name>Specimen</name>
		<pose>Unspecified</pose>
		<truncated>0</truncated>
		<difficult>0</difficult>
		<bndbox>
			<xmin>350</xmin>
			<ymin>30</ymin>
			<xmax>644</xmax>
			<ymax>1719</ymax>
		</bndbox>
	</object>
	<object>
		<name>Specimen</name>
		<pose>Unspecified</pose>
		<truncated>0</truncated>
		<difficult>0</difficult>
		<bndbox>
			<xmin>704</xmin>
			<ymin>92</ymin>
			<xmax>1137</xmax>
			<ymax>1590</ymax>
		</bndbox>
	</object>
</annotation>
